TOPSIS_PANKAJ_101803352/topsis.py
TOPSIS_PANKAJ_101803352-0.4.dist-info/LICENSE.txt
TOPSIS_PANKAJ_101803352-0.4.dist-info/METADATA
TOPSIS_PANKAJ_101803352-0.4.dist-info/WHEEL
TOPSIS_PANKAJ_101803352-0.4.dist-info/top_level.txt
TOPSIS_PANKAJ_101803352-0.4.dist-info/RECORD
