Metadata-Version: 2.1
Name: TOPSIS-PANKAJ-101803352
Version: 0.4
Summary: Multiple Criteria Decision Making using Topsis
Home-page: UNKNOWN
Author: Pankaj Gupta
Author-email: pankaj140699@gmail.com
License: UNKNOWN
Platform: UNKNOWN
Requires-Dist: pandas
